neural_code/__init__.py
neural_code/neural_code.py
neural_code-0.1.0.dist-info/AUTHORS.rst
neural_code-0.1.0.dist-info/LICENSE
neural_code-0.1.0.dist-info/METADATA
neural_code-0.1.0.dist-info/WHEEL
neural_code-0.1.0.dist-info/top_level.txt
neural_code-0.1.0.dist-info/RECORD
