Metadata-Version: 2.1
Name: neural_code
Version: 0.1.0
Summary: A package for analysing neural code.
Home-page: https://github.com/JKilgallen/neural_code
Author: Jack Kilgallen
Author-email: jkilgallen@protonmail.com
License: BSD license
Keywords: neural_code
Platform: UNKNOWN
Classifier: Development Status :: 2 - Pre-Alpha
Classifier: Intended Audience :: Developers
Classifier: License :: OSI Approved :: BSD License
Classifier: Natural Language :: English
Classifier: Programming Language :: Python :: 3
Classifier: Programming Language :: Python :: 3.6
Classifier: Programming Language :: Python :: 3.7
Classifier: Programming Language :: Python :: 3.8
Requires-Python: >=3.6
License-File: LICENSE
License-File: AUTHORS.rst
